<INPUT>
    <FILE type="0"><!-- 0 = training set 1 = testSet -->
        <NAME_FILE io="2">iris.data</NAME_FILE> <!-- io =0 input only, 1 output(label) only, 2 is Io -->
        <NUM_ATTRB>4</NUM_ATTRB>
        <NUM_CLASS>3</NUM_CLASS>
        <NUM_ATTRB_OUTPUT>1</NUM_ATTRB_OUTPUT>
        <NUM_SAMPLE>150</NUM_SAMPLE>
        <CONVERT_METHOD> <!-- 0 string to int, 1 string to double, 2 map table, 3 random(double) 4 random(int) -->
            <METHOD>1</METHOD> <!-- default method -->
        </CONVERT_METHOD>
        <SYMBOL>
            <LINE_START>0</LINE_START>
            <ORDER_ATTRB_START>0</ORDER_ATTRB_START>
            <IO_START>0</IO_START> <!--Optional tag use it when io=2 read 0 Input before output, 1 output before input -->
            <START_OUT>-1</START_OUT>
            <STOP_OUT>-1</STOP_OUT>
            <START_INP>-1</START_INP>
            <STOP_INP>,</STOP_INP>
        </SYMBOL>
    </FILE>
</INPUT>
